{
  "metadata": {
    "date": "1/25/26 2:25 PM",
    "name": "Aniket Solanki",
    "issueType": "Payment Over Due Information",
    "callingNumber": "7458863890",
    "recordingLink": "https://drive.google.com/file/d/1L1L-j8GKai8UyCHyoFVCOZ1rvDdROp1W/view?usp=drive_link",
    "processedAt": "2026-01-31T19:13:01.216Z",
    "callDuration": 180
  },
  "transcription": {
    "agentConversation": [
      {
        "text": "नमस्कार सर, आईटी में स्वागत है। आपकी बात अनिकेत से हो रही है। बताइए, मैं क्या सहायता कर सकता हूँ?",
        "timestamp": 2.64,
        "speaker": "agent"
      },
      {
        "text": "बैटरी बैकअप नहीं दे रही है?",
        "timestamp": 10.32,
        "speaker": "agent"
      },
      {
        "text": "डेट ऑफ बर्थ बताइए।",
        "timestamp": 14.82,
        "speaker": "agent"
      },
      {
        "text": "13/25/1981?",
        "timestamp": 18.24,
        "speaker": "agent"
      },
      {
        "text": "नाम जान सकता हूँ आपका?",
        "timestamp": 30.6,
        "speaker": "agent"
      },
      {
        "text": "और सत्यम मिश्रा के नाम पे आईडी 132581?",
        "timestamp": 35.28,
        "speaker": "agent"
      },
      {
        "text": "बैटरी में क्या दिक्कत आ रही है?",
        "timestamp": 45.18,
        "speaker": "agent"
      },
      {
        "text": "कम चल रही है बैटरी?",
        "timestamp": 51.96,
        "speaker": "agent"
      },
      {
        "text": "आपका ना सर, ये कंप्लेन क्रिएट नहीं हो पा रहा है क्योंकि आपकी ना पेंडिंग अमाउंट है, बहुत ज्यादा पेनल्टी लगी हुई है। ठीक है? तो उसके वजह से कंप्लेन क्रिएट नहीं हो पा रहा है। अब अगर पेमेंट नहीं करोगे ना, तो टीम चेक करके नहीं आ पाएगी क्योंकि कंप्लेन क्रिएट नहीं हो रहा आपका। ठीक है?",
        "timestamp": 54.72,
        "speaker": "agent"
      },
      {
        "text": "तो वो आए नहीं थे चेंज करने के लिए बैटरी?",
        "timestamp": 78.06,
        "speaker": "agent"
      },
      {
        "text": "आपके भी 17,000 का ड्यू अमाउंट यहाँ पे शो कर रहा है कि 17,000 का ड्यू अमाउंट है।",
        "timestamp": 89.88,
        "speaker": "agent"
      },
      {
        "text": "जी।",
        "timestamp": 95.64,
        "speaker": "agent"
      },
      {
        "text": "नहीं, नहीं। ड्यू अमाउंट जो टोटल अभी शो कर रहा है ना, वो 17,000 शो कर रहा है।",
        "timestamp": 99,
        "speaker": "agent"
      },
      {
        "text": "चेक कर लेता हूँ लाइन पर एक बार। आपका दिसंबर का मंथ में आपने पेमेंट नहीं करा था, ₹5,000। और उसकी पेनल्टी लग गई थी ₹1,100। ठीक है? और...",
        "timestamp": 104.04,
        "speaker": "agent"
      },
      {
        "text": "और आपकी फिर नवंबर के महीने में आपने ₹5,000 लीड से करा था, तब तक आपकी ₹47,000 की लग गई थी पेनल्टी ऑलरेडी। ठीक है?",
        "timestamp": 128.16,
        "speaker": "agent"
      },
      {
        "text": "₹47,000 की पेनल्टी लगी थी।",
        "timestamp": 136.08,
        "speaker": "agent"
      },
      {
        "text": "हाँ।",
        "timestamp": 139.14,
        "speaker": "agent"
      },
      {
        "text": "और फिर आपने जनवरी का पेमेंट किया है आपने? नहीं किया ना? जनवरी का पेमेंट कर दिया आपने?",
        "timestamp": 141.66,
        "speaker": "agent"
      },
      {
        "text": "ये भी पेंडिंग ही शो कर रहा है आपका अभी। जनवरी वाला भी पेंडिंग ही शो कर रहा है आपका, ₹5,000 और ₹1,200 पेनल्टी। नहीं, वो भी नहीं हुआ।",
        "timestamp": 149.1,
        "speaker": "agent"
      },
      {
        "text": "ठीक है। और कोई जानकारी सर, आईडी नंबर समेत?",
        "timestamp": 163.56,
        "speaker": "agent"
      },
      {
        "text": "ठीक है। धन्यवाद आईडी नंबर पर कॉल करने के लिए। जानकारी से संतुष्ट रहेंगे तो एक दबाइएगा, अन्यथा दो दबाइएगा। धन्यवाद आपका दिन शुभ हो।",
        "timestamp": 166.98,
        "speaker": "agent"
      }
    ],
    "partnerConversation": [
      {
        "text": "सर, मेरी बैटरी बैकअप नहीं दे रही है।",
        "timestamp": 7.68,
        "speaker": "partner"
      },
      {
        "text": "जी।",
        "timestamp": 12.48,
        "speaker": "partner"
      },
      {
        "text": "13/25/1981।",
        "timestamp": 16.62,
        "speaker": "partner"
      },
      {
        "text": "जी।",
        "timestamp": 20.46,
        "speaker": "partner"
      },
      {
        "text": "सत्यम मिश्रा।",
        "timestamp": 32.52,
        "speaker": "partner"
      },
      {
        "text": "जी।",
        "timestamp": 38.58,
        "speaker": "partner"
      },
      {
        "text": "बैटरी चल नहीं रही, ज्यादा 40-45 चल रही है।",
        "timestamp": 48.48,
        "speaker": "partner"
      },
      {
        "text": "हाँ।",
        "timestamp": 54,
        "speaker": "partner"
      },
      {
        "text": "हम नवंबर से कंप्लेन कर रहे हैं। जब पेमेंट कर रहे थे तब से।",
        "timestamp": 71.88,
        "speaker": "partner"
      },
      {
        "text": "नहीं आए। और इस महीने हमसे बोले कि आप इस महीने किस्त डाल दीजिए, आपकी बैटरी चेंज हो जाएगी, फिर किस्त दे दीजिएगा।",
        "timestamp": 80.64,
        "speaker": "partner"
      },
      {
        "text": "किसी का 17,000 है।",
        "timestamp": 94.2,
        "speaker": "partner"
      },
      {
        "text": "किसी का 17,000 है।",
        "timestamp": 97.26,
        "speaker": "partner"
      },
      {
        "text": "काहे का?",
        "timestamp": 102.6,
        "speaker": "partner"
      },
      {
        "text": "बैटरी अंडरहोल्ड है। तो जब आप लेके गए थे बैटरी, तब आपने चेक नहीं किया था?",
        "timestamp": 123,
        "speaker": "partner"
      },
      {
        "text": "कितना लगा था?",
        "timestamp": 135.06,
        "speaker": "partner"
      },
      {
        "text": "पेनल्टी?",
        "timestamp": 138.3,
        "speaker": "partner"
      },
      {
        "text": "अच्छा।",
        "timestamp": 140.76,
        "speaker": "partner"
      },
      {
        "text": "हाँ।",
        "timestamp": 147.84,
        "speaker": "partner"
      },
      {
        "text": "ठीक है सर, आप बैटरी रहने दीजिए चेंज करने का, हम देंगे भी बैटरी नहीं। ठीक है?",
        "timestamp": 158.7,
        "speaker": "partner"
      },
      {
        "text": "नहीं, कोई जानकारी नहीं चाहिए।",
        "timestamp": 165.36,
        "speaker": "partner"
      },
      {
        "text": "अगर आप हमारे द्वारा दी गई सहायता से खुश हैं, तो एक दबाएँ। अगर नहीं, तो दो दबाएँ। आप।",
        "timestamp": 173.28,
        "speaker": "partner"
      }
    ],
    "fullTranscript": "Agent: नमस्कार सर, आईटी में स्वागत है। आपकी बात अनिकेत से हो रही है। बताइए, मैं क्या सहायता कर सकता हूँ?\n\nPartner: सर, मेरी बैटरी बैकअप नहीं दे रही है।\n\nAgent: बैटरी बैकअप नहीं दे रही है?\n\nPartner: जी।\n\nAgent: डेट ऑफ बर्थ बताइए।\n\nPartner: 13/25/1981।\n\nAgent: 13/25/1981?\n\nPartner: जी।\n\nAgent: नाम जान सकता हूँ आपका?\n\nPartner: सत्यम मिश्रा।\n\nAgent: और सत्यम मिश्रा के नाम पे आईडी 132581?\n\nPartner: जी।\n\nAgent: बैटरी में क्या दिक्कत आ रही है?\n\nPartner: बैटरी चल नहीं रही, ज्यादा 40-45 चल रही है।\n\nAgent: कम चल रही है बैटरी?\n\nPartner: हाँ।\n\nAgent: आपका ना सर, ये कंप्लेन क्रिएट नहीं हो पा रहा है क्योंकि आपकी ना पेंडिंग अमाउंट है, बहुत ज्यादा पेनल्टी लगी हुई है। ठीक है? तो उसके वजह से कंप्लेन क्रिएट नहीं हो पा रहा है। अब अगर पेमेंट नहीं करोगे ना, तो टीम चेक करके नहीं आ पाएगी क्योंकि कंप्लेन क्रिएट नहीं हो रहा आपका। ठीक है?\n\nPartner: हम नवंबर से कंप्लेन कर रहे हैं। जब पेमेंट कर रहे थे तब से।\n\nAgent: तो वो आए नहीं थे चेंज करने के लिए बैटरी?\n\nPartner: नहीं आए। और इस महीने हमसे बोले कि आप इस महीने किस्त डाल दीजिए, आपकी बैटरी चेंज हो जाएगी, फिर किस्त दे दीजिएगा।\n\nAgent: आपके भी 17,000 का ड्यू अमाउंट यहाँ पे शो कर रहा है कि 17,000 का ड्यू अमाउंट है।\n\nPartner: किसी का 17,000 है।\n\nAgent: जी।\n\nPartner: किसी का 17,000 है।\n\nAgent: नहीं, नहीं। ड्यू अमाउंट जो टोटल अभी शो कर रहा है ना, वो 17,000 शो कर रहा है।\n\nPartner: काहे का?\n\nAgent: चेक कर लेता हूँ लाइन पर एक बार। आपका दिसंबर का मंथ में आपने पेमेंट नहीं करा था, ₹5,000। और उसकी पेनल्टी लग गई थी ₹1,100। ठीक है? और...\n\nPartner: बैटरी अंडरहोल्ड है। तो जब आप लेके गए थे बैटरी, तब आपने चेक नहीं किया था?\n\nAgent: और आपकी फिर नवंबर के महीने में आपने ₹5,000 लीड से करा था, तब तक आपकी ₹47,000 की लग गई थी पेनल्टी ऑलरेडी। ठीक है?\n\nPartner: कितना लगा था?\n\nAgent: ₹47,000 की पेनल्टी लगी थी।\n\nPartner: पेनल्टी?\n\nAgent: हाँ।\n\nPartner: अच्छा।\n\nAgent: और फिर आपने जनवरी का पेमेंट किया है आपने? नहीं किया ना? जनवरी का पेमेंट कर दिया आपने?\n\nPartner: हाँ।\n\nAgent: ये भी पेंडिंग ही शो कर रहा है आपका अभी। जनवरी वाला भी पेंडिंग ही शो कर रहा है आपका, ₹5,000 और ₹1,200 पेनल्टी। नहीं, वो भी नहीं हुआ।\n\nPartner: ठीक है सर, आप बैटरी रहने दीजिए चेंज करने का, हम देंगे भी बैटरी नहीं। ठीक है?\n\nAgent: ठीक है। और कोई जानकारी सर, आईडी नंबर समेत?\n\nPartner: नहीं, कोई जानकारी नहीं चाहिए।\n\nAgent: ठीक है। धन्यवाद आईडी नंबर पर कॉल करने के लिए। जानकारी से संतुष्ट रहेंगे तो एक दबाइएगा, अन्यथा दो दबाइएगा। धन्यवाद आपका दिन शुभ हो।\n\nPartner: अगर आप हमारे द्वारा दी गई सहायता से खुश हैं, तो एक दबाएँ। अगर नहीं, तो दो दबाएँ। आप।"
  },
  "analysis": {
    "summary": "The customer called about a battery backup issue with his device, reporting that the battery was not holding charge for long. The agent informed the customer that he cannot create a service complaint due to pending payment amounts and accumulated penalties totaling around ₹47,000. The call ended with the customer declining further service and the agent concluding the interaction without resolving the original battery problem.",
    "problemFaced": "The customer was experiencing poor battery backup, with the battery only lasting 40-45 minutes. Additionally, there were pending payment issues and penalties totaling around ₹17,000, which were preventing the service team from addressing the battery problem. The customer reported they had been trying to get the battery changed since November, but no action had been taken.",
    "solutionPresented": "No clear solution was presented. The agent primarily discussed pending payments and penalties, and did not resolve the partner's battery backup issue. The call ended without addressing the original battery problem, with the partner seemingly frustrated and unwilling to proceed further due to unresolved payment and service concerns.",
    "agentSentiment": {
      "overall": "frustrated",
      "confidence": 0.9,
      "details": "Agent sounds increasingly irritated while discussing pending payments and penalties, speaking firmly and repeatedly emphasizing the customer's outstanding dues. The tone becomes more pointed and less patient as the conversation progresses, with a sense of bureaucratic frustration about unpaid bills blocking service resolution."
    },
    "partnerSentiment": {
      "overall": "frustrated",
      "confidence": 0.9,
      "details": "The partner sounds increasingly frustrated while discussing ongoing battery issues, expressing long-standing complaints, showing irritation about payment and service delays, and speaking with a tone of exasperation about unresolved technical problems"
    },
    "partnerSatisfactionScore": {
      "score": 2,
      "maxScore": 10,
      "reasoning": "The customer's issue was not resolved. The agent focused more on discussing pending payments and penalties rather than addressing the battery backup problem. The customer became increasingly frustrated, ultimately stating they would not even want the battery changed. The agent did not provide a clear solution to the original technical issue, and the conversation ended with the customer seeming dissatisfied and frustrated. The communication was complex, with multiple misunderstandings and a focus on financial disputes rather than customer service. The customer's initial simple request about battery performance was never adequately addressed."
    }
  }
}